napari_easytrack/__init__.py
napari_easytrack/napari.yaml
napari_easytrack/presets.py
napari_easytrack/utils.py
napari_easytrack/analysis/__init__.py
napari_easytrack/analysis/optim_backend.py
napari_easytrack/analysis/optim_manager.py
napari_easytrack/analysis/optim_pipeline.py
napari_easytrack/analysis/tracking.py
napari_easytrack/configs/WD1.1_param_means.json
napari_easytrack/configs/WD3.2_param_means.json
napari_easytrack/configs/cell_config.json
napari_easytrack/configs/disc2_config.json
napari_easytrack/configs/optimized_config_3d.json
napari_easytrack/widgets/__init__.py
napari_easytrack/widgets/optim_widget.py
napari_easytrack/widgets/widget.py
napari_easytrack-0.1.5.dist-info/licenses/LICENSE.md
napari_easytrack-0.1.5.dist-info/METADATA
napari_easytrack-0.1.5.dist-info/WHEEL
napari_easytrack-0.1.5.dist-info/entry_points.txt
napari_easytrack-0.1.5.dist-info/top_level.txt
napari_easytrack-0.1.5.dist-info/RECORD
