Metadata-Version: 2.4
Name: napari-easytrack
Version: 0.1.5
Summary: Cell tracking with btrack presets and parameter optimization
Author-email: Tim Huygelen <tim.huygelen.20@ucl.ac.uk>, Pablo Vicente Munuera <p.munuera@ucl.ac.uk>, Yanlan Mao <y.mao@ucl.ac.uk>
License: Copyright (c), 2025, napari-easytrack developers All rights reserved.
Keywords: biology,cell,tracking,tissue
Classifier: Framework :: napari
Classifier: Intended Audience :: Science/Research
Classifier: Operating System :: OS Independent
Classifier: Programming Language :: Python :: 3
Classifier: Programming Language :: Python :: 3 :: Only
Classifier: Programming Language :: Python :: 3.10
Classifier: Programming Language :: Python :: 3.11
Classifier: Programming Language :: Python :: 3.12
Classifier: Topic :: Scientific/Engineering :: Image Processing
Classifier: Topic :: Scientific/Engineering :: Medical Science Apps.
Classifier: Topic :: Scientific/Engineering :: Bio-Informatics
Requires-Python: >=3.10
License-File: LICENSE.md
Requires-Dist: magicgui
Requires-Dist: napari
Requires-Dist: numpy
Requires-Dist: btrack
Requires-Dist: qtpy
Requires-Dist: scipy
Requires-Dist: scikit-image
Requires-Dist: magicgui
Requires-Dist: optuna
Requires-Dist: joblib
Requires-Dist: traccuracy
Requires-Dist: numba==0.62.1
Provides-Extra: dev
Requires-Dist: black; extra == "dev"
Requires-Dist: mypy; extra == "dev"
Requires-Dist: pre-commit; extra == "dev"
Requires-Dist: pyqt5; extra == "dev"
Requires-Dist: ruff; extra == "dev"
Requires-Dist: tox; extra == "dev"
Provides-Extra: docs
Requires-Dist: myst-parser; extra == "docs"
Requires-Dist: pydata-sphinx-theme; extra == "docs"
Requires-Dist: pytz; extra == "docs"
Requires-Dist: sphinx-autobuild; extra == "docs"
Requires-Dist: sphinx; extra == "docs"
Requires-Dist: sphinx_autodoc_typehints; extra == "docs"
Requires-Dist: sphinxcontrib-video; extra == "docs"
Requires-Dist: types-pytz; extra == "docs"
Requires-Dist: sphinx-rtd-theme; extra == "docs"
Requires-Dist: pyqt5; extra == "docs"
Provides-Extra: testing
Requires-Dist: pytest; extra == "testing"
Requires-Dist: pytest-cov; extra == "testing"
Requires-Dist: tox; extra == "testing"
Requires-Dist: imagecodecs; extra == "testing"
Requires-Dist: coverage; extra == "testing"
Dynamic: license-file
